django_soc_lite/HTML_Escape.py
django_soc_lite/__init__.py
django_soc_lite/logger.py
django_soc_lite/rule_checker.py
django_soc_lite/rules.json
django_soc_lite/runtests.py
django_soc_lite/url_coder.py
django_soc_lite/verify.py
django_soc_lite/tests/__init__.py
django_soc_lite/tests/rule_test.py
django_soc_lite/tests/test_middleware.py
django_soc_lite/threat/__init__.py
django_soc_lite/threat/decorators.py
django_soc_lite/threat/directory_traversal.py
django_soc_lite/threat/log_generator.py
django_soc_lite/threat/middleware.py
django_soc_lite/threat/sample_monkey.py
django_soc_lite/threat/secure_headers.py
django_soc_lite/threat/sql.py
django_soc_lite/threat/tests.py
django_soc_lite/threat/xss.py
django_soc_lite/threat/error_page/__init__.py
django_soc_lite-0.0.4.dist-info/LICENSE
django_soc_lite-0.0.4.dist-info/METADATA
django_soc_lite-0.0.4.dist-info/WHEEL
django_soc_lite-0.0.4.dist-info/top_level.txt
django_soc_lite-0.0.4.dist-info/RECORD
