Metadata-Version: 2.1
Name: django-soc-lite
Version: 0.0.4
Summary: A Powerfull Django plugin to detect and logging Basic Web-based Attack.
Home-page: https://github.com/threatequation/django-soc-lite
Author: threatequation
Author-email: contact@threatequation.com
Maintainer: threatequation
License: UNKNOWN
Platform: UNKNOWN
Classifier: Development Status :: 3 - Alpha
Classifier: Environment :: Web Environment
Classifier: Intended Audience :: Developers
Classifier: Operating System :: OS Independent
Classifier: Programming Language :: Python
Classifier: Programming Language :: Python :: 3
Classifier: Programming Language :: Python :: 3.5
Classifier: Programming Language :: Python :: 3.6
Classifier: Programming Language :: Python :: 3.7
Classifier: Framework :: Django
Requires-Dist: click (==6.6)
Requires-Dist: requests (==2.20.0)
Requires-Dist: requests-cache (==0.4.13)
Requires-Dist: shellescape (==3.4.1)
